<?xml version="1.0" encoding="utf-8"?>
<importJob xmlns:xsi="http://www.w3.org/2001/XMLSchema-instance"
           xsi:schemaLocation="http://www4.wiwiss.fu-berlin.de/ldif/ ../../xsd/ImportJob.xsd"
           xmlns="http://www4.wiwiss.fu-berlin.de/ldif/">
    <internalId>en.dbpedia.org</internalId>
    <dataSource>DBpedia</dataSource>
    <refreshSchedule>onStartup</refreshSchedule>
    <tripleImportJob>
        <dumpLocation>http://sieve.wbsg.de/download/lwdm2012/en.nq.bz2</dumpLocation>
    </tripleImportJob>
</importJob>